gmr/__init__.py
gmr/gmm.py
gmr/mvn.py
gmr/sklearn.py
gmr/utils.py
gmr-2.0.2.dist-info/licenses/LICENSE
gmr-2.0.2.dist-info/METADATA
gmr-2.0.2.dist-info/WHEEL
gmr-2.0.2.dist-info/top_level.txt
gmr-2.0.2.dist-info/RECORD
