Metadata-Version: 2.4
Name: gmr
Version: 2.0.2
Summary: Gaussian Mixture Regression
Author-email: Alexander Fabisch <alexander.fabisch@dfki.de>
Maintainer-email: Alexander Fabisch <alexander.fabisch@dfki.de>
License-Expression: BSD-3-Clause
Project-URL: Homepage, https://github.com/AlexanderFabisch/gmr
Project-URL: Issues, https://github.com/AlexanderFabisch/gmr/issues
Classifier: Intended Audience :: Science/Research
Classifier: Intended Audience :: Developers
Classifier: Programming Language :: Python
Classifier: Topic :: Software Development
Classifier: Topic :: Scientific/Engineering
Classifier: Operating System :: Microsoft :: Windows
Classifier: Operating System :: POSIX
Classifier: Operating System :: Unix
Classifier: Operating System :: MacOS
Classifier: Programming Language :: Python :: 2
Classifier: Programming Language :: Python :: 2.7
Classifier: Programming Language :: Python :: 3
Classifier: Programming Language :: Python :: 3.4
Classifier: Programming Language :: Python :: 3.5
Classifier: Programming Language :: Python :: 3.6
Classifier: Programming Language :: Python :: 3.7
Classifier: Programming Language :: Python :: 3.8
Classifier: Programming Language :: Python :: 3.9
Classifier: Programming Language :: Python :: 3.10
Classifier: Programming Language :: Python :: 3.11
Classifier: Programming Language :: Python :: 3.12
Classifier: Programming Language :: Python :: 3.13
Requires-Python: >=2.7
License-File: LICENSE
Requires-Dist: numpy
Requires-Dist: scipy
Provides-Extra: all
Requires-Dist: matplotlib; extra == "all"
Requires-Dist: scikit-learn; extra == "all"
Requires-Dist: svgpathtools; extra == "all"
Provides-Extra: test
Requires-Dist: pytest; extra == "test"
Requires-Dist: pytest-cov; extra == "test"
Provides-Extra: doc
Requires-Dist: pdoc3; extra == "doc"
Dynamic: license-file
